{
  "manifestVersion": "3.2",
  "admin": {
    "address": "0x9fE46736679d2D9a65F0992F2272dE9f3c7fa6e0",
    "txHash": "0x96081bb86f9570b068e6e41afa46ad289f9a8ef43ef47c70fb172f158ad23692"
  },
  "proxies": [
    {
      "address": "0xdB012DD3E3345e2f8D23c0F3cbCb2D94f430Be8C",
      "txHash": "0x66e4c21a30884b2b4bfad69a7a20973ad8e44865aa420656276cdd80742dfe4c",
      "kind": "transparent"
    },
    {
      "address": "0x9fE46736679d2D9a65F0992F2272dE9f3c7fa6e0",
      "txHash": "0xd6334b6b675db2ff74809b02c6c3d21d59c6e9e9e9317cb03de8a1776876424c",
      "kind": "transparent"
    },
    {
      "address": "0x2279B7A0a67DB372996a5FaB50D91eAA73d2eBe6",
      "txHash": "0x9df88a8c8052e592fe7374a19781d746694963df7245901c621716cb84995032",
      "kind": "transparent"
    },
    {
      "address": "0x8A791620dd6260079BF849Dc5567aDC3F2FdC318",
      "txHash": "0xa677884e4e9442461e814e2ea5852f9548362f4d2a3f398ad307358a361dfdcd",
      "kind": "transparent"
    },
    {
      "address": "0xDc64a140Aa3E981100a9becA4E685f962f0cF6C9",
      "txHash": "0x666cefe9e342f5ae63fd300b12776cd4792f9d3901f96197a204c0de71e2ddb7",
      "kind": "transparent"
    },
    {
      "address": "0xCf7Ed3AccA5a467e9e704C703E8D87F634fB0Fc9",
      "txHash": "0x936e47d5c0285f67ad9eb2ef2cea2691f7f82f79593f92bb71382d8aa5598d29",
      "kind": "transparent"
    }
  ],
  "impls": {
    "4cff6b9266620d9c36049b8e4874350148b70f3f54440857abe3b5614bbd7e69": {
      "address": "0xe7f1725E7734CE288F8367e1Bb143E90bb3F0512",
      "txHash": "0x92580458463af7465b60cc763c6f1b8a6a5145e76ac9b074a8628cd7bc2daff9",
      "layout": {
        "solcVersion": "0.8.9",
        "storage": [
          {
            "label": "_initialized",
            "offset": 0,
            "slot": "0",
            "type": "t_uint8",
            "contract": "Initializable",
            "src": "@openzeppelin\\contracts-upgradeable\\proxy\\utils\\Initializable.sol:62",
            "retypedFrom": "bool"
          },
          {
            "label": "_initializing",
            "offset": 1,
            "slot": "0",
            "type": "t_bool",
            "contract": "Initializable",
            "src": "@openzeppelin\\contracts-upgradeable\\proxy\\utils\\Initializable.sol:67"
          },
          {
            "label": "count",
            "offset": 0,
            "slot": "1",
            "type": "t_uint256",
            "contract": "CrowdFundingV1",
            "src": "contracts\\CrowdFundingV1.sol:32"
          },
          {
            "label": "maxDuration",
            "offset": 0,
            "slot": "2",
            "type": "t_uint256",
            "contract": "CrowdFundingV1",
            "src": "contracts\\CrowdFundingV1.sol:33"
          },
          {
            "label": "campaigns",
            "offset": 0,
            "slot": "3",
            "type": "t_mapping(t_uint256,t_struct(Campaign)3156_storage)",
            "contract": "CrowdFundingV1",
            "src": "contracts\\CrowdFundingV1.sol:34"
          },
          {
            "label": "pledgedAmount",
            "offset": 0,
            "slot": "4",
            "type": "t_mapping(t_uint256,t_mapping(t_address,t_uint256))",
            "contract": "CrowdFundingV1",
            "src": "contracts\\CrowdFundingV1.sol:35"
          }
        ],
        "types": {
          "t_address": {
            "label": "address",
            "numberOfBytes": "20"
          },
          "t_bool": {
            "label": "bool",
            "numberOfBytes": "1"
          },
          "t_mapping(t_address,t_uint256)": {
            "label": "mapping(address => uint256)",
            "numberOfBytes": "32"
          },
          "t_mapping(t_uint256,t_mapping(t_address,t_uint256))": {
            "label": "mapping(uint256 => mapping(address => uint256))",
            "numberOfBytes": "32"
          },
          "t_mapping(t_uint256,t_struct(Campaign)3156_storage)": {
            "label": "mapping(uint256 => struct CrowdFundingV1.Campaign)",
            "numberOfBytes": "32"
          },
          "t_struct(Campaign)3156_storage": {
            "label": "struct CrowdFundingV1.Campaign",
            "members": [
              {
                "label": "creator",
                "type": "t_address",
                "offset": 0,
                "slot": "0"
              },
              {
                "label": "token",
                "type": "t_address",
                "offset": 0,
                "slot": "1"
              },
              {
                "label": "goal",
                "type": "t_uint256",
                "offset": 0,
                "slot": "2"
              },
              {
                "label": "pledged",
                "type": "t_uint256",
                "offset": 0,
                "slot": "3"
              },
              {
                "label": "startAt",
                "type": "t_uint256",
                "offset": 0,
                "slot": "4"
              },
              {
                "label": "endAt",
                "type": "t_uint256",
                "offset": 0,
                "slot": "5"
              },
              {
                "label": "claimed",
                "type": "t_bool",
                "offset": 0,
                "slot": "6"
              }
            ],
            "numberOfBytes": "224"
          },
          "t_uint256": {
            "label": "uint256",
            "numberOfBytes": "32"
          },
          "t_uint8": {
            "label": "uint8",
            "numberOfBytes": "1"
          }
        }
      }
    }
  }
}
